lazybam-0.2.0.dist-info/METADATA
lazybam-0.2.0.dist-info/WHEEL
lazybam.libs/libgcc_s-5b5488a6.so.1
lazybam/__init__.py
lazybam/error.py
lazybam/header.py
lazybam/lazybam.cpython-313-arm-linux-musleabihf.so
lazybam/lazybam.pyi
lazybam/py.typed
lazybam-0.2.0.dist-info/RECORD
